mlx_cuda/__init__.py
mlx_cuda_14-0.0.0.dist-info/METADATA
mlx_cuda_14-0.0.0.dist-info/WHEEL
mlx_cuda_14-0.0.0.dist-info/top_level.txt
mlx_cuda_14-0.0.0.dist-info/RECORD
