Metadata-Version: 2.4
Name: mlx-cuda-14
Version: 0.0.0
Summary: MLX CUDA 14
Home-page: https://github.com/ml-explore/mlx
Author: MLX Contributors
Author-email: mlx@group.apple.com
License: MIT
Requires-Python: >=3.10
Dynamic: author
Dynamic: author-email
Dynamic: home-page
Dynamic: license
Dynamic: requires-python
Dynamic: summary
